{"SURVIVAL":{"potions":[],"offHandItem":{"==":"org.bukkit.inventory.ItemStack","type":"DIAMOND_PICKAXE","damage":1052,"meta":{"==":"ItemMeta","meta-type":"UNSPECIFIC","enchants":{"MENDING":1},"repair-cost":1}},"inventoryContents":{"27":{"==":"org.bukkit.inventory.ItemStack","type":"ELYTRA","damage":127,"meta":{"==":"ItemMeta","meta-type":"UNSPECIFIC","enchants":{"DURABILITY":3,"MENDING":1},"repair-cost":3}},"31":{"==":"org.bukkit.inventory.ItemStack","type":"TOTEM"},"10":{"==":"org.bukkit.inventory.ItemStack","type":"ROTTEN_FLESH","amount":10},"32":{"==":"org.bukkit.inventory.ItemStack","type":"GOLDEN_APPLE","damage":1,"amount":2},"11":{"==":"org.bukkit.inventory.ItemStack","type":"GLOWSTONE_DUST","amount":4},"33":{"==":"org.bukkit.inventory.ItemStack","type":"ANVIL","damage":2},"12":{"==":"org.bukkit.inventory.ItemStack","type":"ENDER_PEARL","amount":2},"34":{"==":"org.bukkit.inventory.ItemStack","type":"GOLDEN_APPLE","amount":64},"13":{"==":"org.bukkit.inventory.ItemStack","type":"APPLE","meta":{"==":"ItemMeta","meta-type":"UNSPECIFIC","display-name":"§aThe Healing Heart","lore":["§aUse this item to increase your maximum health."],"enchants":{"LURE":1},"ItemFlags":["HIDE_ENCHANTS"],"internal":"H4sIAAAAAAAA\/+NiYGBjEM5ITSwq0QWSOSUZuskZiXnpqQ4MEMDIwAqWZWQAAIAUp6srAAAA"}},"35":{"==":"org.bukkit.inventory.ItemStack","type":"TOTEM"},"14":{"==":"org.bukkit.inventory.ItemStack","type":"STONE","damage":1},"36":{"==":"org.bukkit.inventory.ItemStack","type":"DIAMOND_BOOTS","damage":261,"meta":{"==":"ItemMeta","meta-type":"UNSPECIFIC","enchants":{"PROTECTION_ENVIRONMENTAL":4,"DURABILITY":3,"MENDING":1},"repair-cost":7}},"15":{"==":"org.bukkit.inventory.ItemStack","type":"GOLD_NUGGET","amount":8},"37":{"==":"org.bukkit.inventory.ItemStack","type":"DIAMOND_LEGGINGS","damage":324,"meta":{"==":"ItemMeta","meta-type":"UNSPECIFIC","enchants":{"PROTECTION_ENVIRONMENTAL":4,"DURABILITY":3,"MENDING":1},"repair-cost":7}},"16":{"==":"org.bukkit.inventory.ItemStack","type":"GOLD_SWORD","damage":26},"38":{"==":"org.bukkit.inventory.ItemStack","type":"DIAMOND_CHESTPLATE","damage":60,"meta":{"==":"ItemMeta","meta-type":"UNSPECIFIC","enchants":{"PROTECTION_ENVIRONMENTAL":4,"DURABILITY":3,"MENDING":1},"repair-cost":7}},"17":{"==":"org.bukkit.inventory.ItemStack","type":"STICK","amount":2},"39":{"==":"org.bukkit.inventory.ItemStack","type":"DIAMOND_HELMET","damage":45,"meta":{"==":"ItemMeta","meta-type":"UNSPECIFIC","enchants":{"PROTECTION_ENVIRONMENTAL":4,"DURABILITY":3,"MENDING":1},"repair-cost":7}},"0":{"==":"org.bukkit.inventory.ItemStack","type":"DIAMOND_SWORD","meta":{"==":"ItemMeta","meta-type":"UNSPECIFIC","enchants":{"DAMAGE_ALL":5,"KNOCKBACK":2,"FIRE_ASPECT":2,"LOOT_BONUS_MOBS":3,"DURABILITY":3,"MENDING":1},"repair-cost":63}},"1":{"==":"org.bukkit.inventory.ItemStack","type":"IRON_PICKAXE","damage":109,"meta":{"==":"ItemMeta","meta-type":"UNSPECIFIC","enchants":{"DIG_SPEED":5,"DURABILITY":3,"LOOT_BONUS_BLOCKS":3,"MENDING":1},"repair-cost":15}},"2":{"==":"org.bukkit.inventory.ItemStack","type":"DIAMOND_AXE","damage":132,"meta":{"==":"ItemMeta","meta-type":"UNSPECIFIC","lore":["§8qadata:0"],"enchants":{"DAMAGE_ALL":5,"KNOCKBACK":2,"FIRE_ASPECT":2,"DIG_SPEED":5,"DURABILITY":3,"MENDING":1},"repair-cost":63}},"3":{"==":"org.bukkit.inventory.ItemStack","type":"BOW","damage":1,"meta":{"==":"ItemMeta","meta-type":"UNSPECIFIC","enchants":{"DURABILITY":3,"ARROW_DAMAGE":5,"ARROW_KNOCKBACK":2,"ARROW_FIRE":1,"ARROW_INFINITE":1,"MENDING":1},"repair-cost":31}},"4":{"==":"org.bukkit.inventory.ItemStack","type":"SKULL_ITEM","damage":3,"meta":{"==":"ItemMeta","meta-type":"SKULL","display-name":"§eBackpack","internal":"H4sIAAAAAAAA\/02Py26CQBhG\/zZpQkkfo1sSKIzoootGvAzRmYLcd1x+izhYo1BlnqsPWJZdfjnnLD4VQIWX3bEX4vPyvT8IVOCRVvCKFbGxKIlm6xZqZpEb2hSNXDPQtq1qOrWIaaqgjtEZL90Br8+gdHjv+gteVQB4UOApykWP8IuDq2dJrVeJK8qBTsYd7HTBaXO26Skaijmd0Hbk64\/JZpj9c0mXx0SkpltnJ68v2kjfmL7AtW+UbfjDV36TykykjXfLGnZIY79mzlIwZyt58GXxlfeWOfTGpCeZDAlfuce09e5MRs22Dc2tXNx5sDyyeEHSwBsyhzV87s72if4+PoA\/VbqJgxwBAAA="}},"5":{"==":"org.bukkit.inventory.ItemStack","type":"PURPLE_SHULKER_BOX","meta":{"==":"ItemMeta","meta-type":"TILE_ENTITY","internal":"H4sIAAAAAAAA\/72STUvDQBCGJx+tbQ4eWkFR8eDP8KhW8CbUe9gm083QzWzJjhX\/gX9aMGlaWptYsEhPC7v7Ps\/L7EYAEZzeG5vMRiwkH69K96HzLJi7CMpDD8KxsQI98CmF85wYk0JN5c7NjXJZPLdClj3oPNg3Fi+CQJTuQfdluQ83m4CxrOMpFRgX6MiJ4gTBh+6jypXG0rVSeQeqhluBd5oKo3NtfP9A\/mArIAWylqwNHxyIv9qZFPGCHE3IlI\/S5unVnotNDDnJFAum8cTa2Y6oD4Ox2ALTUX0rR5blC3s+BGZhqrXiPUGbrP\/PsqCW3bbKomPKBg1ZSiq3nMYZmhylIQurMhU+WOHDGl\/Rf+r2DPZzrR\/W+uumPsnQSflzBH+vEO6vcPKXSl\/rSmd1pctmJYNaE2t3lEJeUsa\/AQNoanifBAAA","blockMaterial":"PURPLE_SHULKER_BOX"}},"6":{"==":"org.bukkit.inventory.ItemStack","type":"ANVIL","damage":1},"7":{"==":"org.bukkit.inventory.ItemStack","type":"NETHERRACK","amount":64},"8":{"==":"org.bukkit.inventory.ItemStack","type":"COOKED_BEEF","amount":12},"9":{"==":"org.bukkit.inventory.ItemStack","type":"ARROW","amount":5},"40":{"==":"org.bukkit.inventory.ItemStack","type":"DIAMOND_PICKAXE","damage":1052,"meta":{"==":"ItemMeta","meta-type":"UNSPECIFIC","enchants":{"MENDING":1},"repair-cost":1}},"21":{"==":"org.bukkit.inventory.ItemStack","type":"NETHERRACK","amount":20}},"enderChestContents":{},"armorContents":{"0":{"==":"org.bukkit.inventory.ItemStack","type":"DIAMOND_BOOTS","damage":261,"meta":{"==":"ItemMeta","meta-type":"UNSPECIFIC","enchants":{"PROTECTION_ENVIRONMENTAL":4,"DURABILITY":3,"MENDING":1},"repair-cost":7}},"1":{"==":"org.bukkit.inventory.ItemStack","type":"DIAMOND_LEGGINGS","damage":324,"meta":{"==":"ItemMeta","meta-type":"UNSPECIFIC","enchants":{"PROTECTION_ENVIRONMENTAL":4,"DURABILITY":3,"MENDING":1},"repair-cost":7}},"2":{"==":"org.bukkit.inventory.ItemStack","type":"DIAMOND_CHESTPLATE","damage":60,"meta":{"==":"ItemMeta","meta-type":"UNSPECIFIC","enchants":{"PROTECTION_ENVIRONMENTAL":4,"DURABILITY":3,"MENDING":1},"repair-cost":7}},"3":{"==":"org.bukkit.inventory.ItemStack","type":"DIAMOND_HELMET","damage":45,"meta":{"==":"ItemMeta","meta-type":"UNSPECIFIC","enchants":{"PROTECTION_ENVIRONMENTAL":4,"DURABILITY":3,"MENDING":1},"repair-cost":7}}},"stats":{"ex":"1.2384933","ma":"300","fl":"16","el":"6","hp":"28.716922760009766","xp":"0.8999843","txp":"485","fd":"0.0","sa":"0.0","ft":"-20","ra":"300"}}}