{"stats":{"minecraft:mined":{"minecraft:spawner":2,"minecraft:granite":42,"minecraft:vine":5,"minecraft:smooth_basalt":4,"minecraft:glass":2,"minecraft:diorite":49,"minecraft:cobblestone":26,"minecraft:gravel":4,"minecraft:amethyst_block":3,"minecraft:short_grass":18,"minecraft:oak_leaves":1,"minecraft:furnace":2,"minecraft:clay":4,"minecraft:crafting_table":8,"minecraft:flowering_azalea":1,"minecraft:jungle_log":4,"minecraft:obsidian":4,"minecraft:tall_grass":2,"minecraft:melon":9,"minecraft:pointed_dripstone":2,"minecraft:enchanting_table":1,"minecraft:dirt":20,"minecraft:andesite":26,"minecraft:oak_fence":3,"minecraft:grass_block":5,"minecraft:cobweb":1,"minecraft:moss_block":1,"minecraft:bamboo":2,"minecraft:moss_carpet":1,"minecraft:budding_amethyst":1,"minecraft:fern":1,"minecraft:deepslate":20,"minecraft:calcite":5,"minecraft:small_dripleaf":1,"minecraft:dripstone_block":3,"minecraft:oak_log":9,"minecraft:jungle_leaves":1,"minecraft:stone":565},"minecraft:custom":{"minecraft:time_since_rest":125413,"minecraft:leave_game":13,"minecraft:damage_taken":9266,"minecraft:mob_kills":11,"minecraft:time_since_death":125388,"minecraft:aviate_one_cm":12941,"minecraft:open_enderchest":3,"minecraft:interact_with_furnace":22,"minecraft:swim_one_cm":10544,"minecraft:total_world_time":261237,"minecraft:crouch_one_cm":16126,"minecraft:deaths":10,"minecraft:climb_one_cm":3338,"minecraft:player_kills":3,"minecraft:enchant_item":4,"minecraft:damage_blocked_by_shield":1253,"minecraft:interact_with_crafting_table":16,"minecraft:walk_one_cm":583219,"minecraft:walk_under_water_one_cm":9921,"minecraft:damage_dealt":3090,"minecraft:play_time":261237,"minecraft:jump":2292,"minecraft:drop":111,"minecraft:sprint_one_cm":465930,"minecraft:open_chest":9,"minecraft:fall_one_cm":142968,"minecraft:fly_one_cm":239821,"minecraft:walk_on_water_one_cm":27617,"minecraft:sneak_time":6144},"minecraft:killed_by":{"minecraft:player":3,"minecraft:zombie":3},"minecraft:picked_up":{"minecraft:name_tag":1,"minecraft:enchanting_table":1,"minecraft:cobblestone":594,"minecraft:bone":1,"minecraft:netherite_boots":1,"minecraft:redstone":20,"minecraft:clay_ball":48,"minecraft:melon_slice":77,"minecraft:moss_carpet":1,"minecraft:diamond":7,"minecraft:granite":46,"minecraft:golden_apple":1,"minecraft:glow_ink_sac":19,"minecraft:bamboo":42,"minecraft:moss_block":1,"minecraft:player_head":3,"minecraft:bow":2,"minecraft:smooth_basalt":4,"minecraft:iron_ingot":2,"minecraft:raw_iron":70,"minecraft:cobbled_deepslate":21,"minecraft:pointed_dripstone":4,"minecraft:detector_rail":4,"minecraft:amethyst_block":3,"minecraft:netherite_leggings":1,"minecraft:lava_bucket":2,"minecraft:nautilus_shell":1,"minecraft:netherite_helmet":1,"minecraft:elytra":1,"minecraft:dirt":43,"minecraft:skeleton_skull":1,"minecraft:rail":27,"minecraft:gravel":4,"minecraft:torch":17,"minecraft:dripstone_block":2,"minecraft:zombie_head":2,"minecraft:leaf_litter":5,"minecraft:coal":105,"minecraft:oak_log":9,"minecraft:oak_fence":3,"minecraft:furnace":2,"minecraft:wheat_seeds":5,"minecraft:lapis_lazuli":263,"minecraft:spider_eye":1,"minecraft:jungle_log":4,"minecraft:diorite":51,"minecraft:crafting_table":8,"minecraft:raw_copper":184,"minecraft:andesite":34,"minecraft:rotten_flesh":3,"minecraft:beetroot_seeds":4,"minecraft:string":6,"minecraft:obsidian":4,"minecraft:calcite":6},"minecraft:killed":{"minecraft:zombie":5,"minecraft:skeleton":1,"minecraft:bat":1,"minecraft:spider":4},"minecraft:dropped":{"minecraft:rotten_flesh":3,"minecraft:pointed_dripstone":4,"minecraft:andesite":18,"minecraft:lava_bucket":1,"minecraft:detector_rail":4,"minecraft:wooden_sword":1,"minecraft:bow":2,"minecraft:cobbled_deepslate":1,"minecraft:bone":1,"minecraft:bucket":1,"minecraft:diamond_helmet":1,"minecraft:raw_copper":237,"minecraft:diamond_boots":1,"minecraft:wheat_seeds":6,"minecraft:diamond_chestplate":1,"minecraft:melon_slice":1,"minecraft:diamond_leggings":1,"minecraft:rail":27,"minecraft:beetroot_seeds":4,"minecraft:bamboo":38,"minecraft:redstone":20,"minecraft:leaf_litter":5,"minecraft:diamond_pickaxe":1,"minecraft:string":2,"minecraft:wooden_pickaxe":1,"minecraft:diamond_sword":1,"minecraft:clay_ball":44,"minecraft:spider_eye":1,"minecraft:diorite":51,"minecraft:golden_apple":1,"minecraft:glow_ink_sac":16},"minecraft:used":{"minecraft:stone_axe":3,"minecraft:oak_fence":3,"minecraft:grass_block":1,"minecraft:iron_axe":1,"minecraft:diamond_helmet":1,"minecraft:shield":16,"minecraft:end_crystal":3,"minecraft:iron_pickaxe":627,"minecraft:andesite":23,"minecraft:bamboo":4,"minecraft:elytra":1,"minecraft:diamond_pickaxe":8,"minecraft:wooden_sword":1,"minecraft:granite":6,"minecraft:lava_bucket":2,"minecraft:wooden_pickaxe":15,"minecraft:diamond_leggings":1,"minecraft:mace":8,"minecraft:cobblestone":270,"minecraft:diamond_chestplate":1,"minecraft:diamond_axe":79,"minecraft:crafting_table":11,"minecraft:iron_chestplate":1,"minecraft:moss_block":1,"minecraft:stone_pickaxe":123,"minecraft:calcite":6,"minecraft:diamond_boots":1,"minecraft:netherite_helmet":1,"minecraft:iron_leggings":2,"minecraft:cobbled_deepslate":20,"minecraft:moss_carpet":1,"minecraft:melon_slice":16,"minecraft:water_bucket":30,"minecraft:netherite_boots":2,"minecraft:netherite_leggings":1,"minecraft:smooth_basalt":4,"minecraft:furnace":2,"minecraft:dirt":11,"minecraft:iron_boots":2,"minecraft:obsidian":70,"minecraft:wind_charge":1,"minecraft:diamond_ore":5,"minecraft:ender_chest":3,"minecraft:bucket":32,"minecraft:amethyst_block":3,"minecraft:chest":1,"minecraft:splash_potion":4,"minecraft:iron_helmet":2,"minecraft:dripstone_block":2,"minecraft:enchanting_table":1},"minecraft:broken":{"minecraft:iron_pickaxe":3,"minecraft:stone_pickaxe":1},"minecraft:crafted":{"minecraft:bucket":1,"minecraft:furnace":2,"minecraft:jungle_planks":16,"minecraft:iron_ingot":41,"minecraft:wooden_sword":1,"minecraft:stone_pickaxe":1,"minecraft:iron_chestplate":1,"minecraft:iron_boots":1,"minecraft:crafting_table":4,"minecraft:stick":24,"minecraft:wooden_pickaxe":1,"minecraft:shield":1,"minecraft:stone_axe":1,"minecraft:oak_planks":36,"minecraft:iron_helmet":1,"minecraft:diamond_axe":1,"minecraft:diamond_pickaxe":1,"minecraft:enchanting_table":1,"minecraft:iron_pickaxe":3,"minecraft:air":0}},"DataVersion":4440}